uwuify/__init__.py
uwuify/__main__.py
uwuify/cli.py
uwuify/core.py
uwuify-1.3.0.dist-info/LICENSE
uwuify-1.3.0.dist-info/METADATA
uwuify-1.3.0.dist-info/WHEEL
uwuify-1.3.0.dist-info/entry_points.txt
uwuify-1.3.0.dist-info/RECORD
