Metadata-Version: 2.1
Name: uwuify
Version: 1.3.0
Summary: uwuifys text
Home-page: https://github.com/StarrFox/uwuify
License: MIT
Author: StarrFox
Author-email: starrfox6312@gmail.com
Requires-Python: >=3.7,<4.0
Classifier: License :: OSI Approved :: MIT License
Classifier: Programming Language :: Python :: 3
Classifier: Programming Language :: Python :: 3.7
Classifier: Programming Language :: Python :: 3.8
Classifier: Programming Language :: Python :: 3.9
Classifier: Programming Language :: Python :: 3.10
Classifier: Programming Language :: Python :: 3.11
Requires-Dist: click (>=8.0.1,<9.0.0)
Project-URL: Repository, https://github.com/StarrFox/uwuify
